odoo9_addon_l10n_ch_pain_credit_transfer-9.0.1.0.0.99.dev16-py2.7-nspkg.pth
odoo9_addon_l10n_ch_pain_credit_transfer-9.0.1.0.0.99.dev16.dist-info/METADATA
odoo9_addon_l10n_ch_pain_credit_transfer-9.0.1.0.0.99.dev16.dist-info/RECORD
odoo9_addon_l10n_ch_pain_credit_transfer-9.0.1.0.0.99.dev16.dist-info/WHEEL
odoo9_addon_l10n_ch_pain_credit_transfer-9.0.1.0.0.99.dev16.dist-info/namespace_packages.txt
odoo9_addon_l10n_ch_pain_credit_transfer-9.0.1.0.0.99.dev16.dist-info/top_level.txt
odoo_addons/l10n_ch_pain_credit_transfer/README.rst
odoo_addons/l10n_ch_pain_credit_transfer/__init__.py
odoo_addons/l10n_ch_pain_credit_transfer/__openerp__.py
odoo_addons/l10n_ch_pain_credit_transfer/data/pain.001.001.03.ch.02.xsd
odoo_addons/l10n_ch_pain_credit_transfer/i18n/ca.po
odoo_addons/l10n_ch_pain_credit_transfer/i18n/de.po
odoo_addons/l10n_ch_pain_credit_transfer/i18n/es.po
odoo_addons/l10n_ch_pain_credit_transfer/i18n/fr.po
odoo_addons/l10n_ch_pain_credit_transfer/i18n/l10n_ch_pain_credit_transfer.pot
odoo_addons/l10n_ch_pain_credit_transfer/i18n/nb_NO.po
odoo_addons/l10n_ch_pain_credit_transfer/i18n/pt_BR.po
odoo_addons/l10n_ch_pain_credit_transfer/models/__init__.py
odoo_addons/l10n_ch_pain_credit_transfer/models/account_payment_method.py
odoo_addons/l10n_ch_pain_credit_transfer/static/description/icon.png
odoo_addons/l10n_ch_pain_credit_transfer/tests/__init__.py
odoo_addons/l10n_ch_pain_credit_transfer/tests/test_ch_sct.py
