Metadata-Version: 2.1
Name: odoo9-addon-l10n-ch-pain-credit-transfer
Version: 9.0.1.0.0.99.dev16
Summary: Generate ISO 20022 credit transfert (SEPA and not SEPA)
Home-page: UNKNOWN
Author: Akretion,Camptocamp,Odoo Community Association (OCA)
Author-email: support@odoo-community.org
License: AGPL-3
Platform: UNKNOWN
Classifier: Programming Language :: Python
Classifier: Framework :: Odoo
Classifier: License :: OSI Approved :: GNU Affero General Public License v3
Requires-Python: ~=2.7
Requires-Dist: odoo9-addon-account-banking-sepa-credit-transfer
Requires-Dist: odoo9-addon-l10n-ch-pain-base
Requires-Dist: odoo (<9.1a,>=9.0a)
